CHANGELOG.md
psychrochart/__init__.py
psychrochart/__main__.py
psychrochart/chart.py
psychrochart/chart_entities.py
psychrochart/chart_styles/ashrae_chart_style.json
psychrochart/chart_styles/ashrae_ip_chart_style.json
psychrochart/chart_styles/default_chart_config.json
psychrochart/chart_styles/default_comfort_zones.json
psychrochart/chart_styles/interior_chart_style.json
psychrochart/chart_styles/minimal_chart_style.json
psychrochart/chartdata.py
psychrochart/chartzones.py
psychrochart/models/__init__.py
psychrochart/models/annots.py
psychrochart/models/base.py
psychrochart/models/config.py
psychrochart/models/curves.py
psychrochart/models/parsers.py
psychrochart/models/styles.py
psychrochart/models/validators.py
psychrochart/plot_logic.py
psychrochart/process_logic.py
psychrochart/util.py
psychrochart-0.11.1.dist-info/LICENSE
psychrochart-0.11.1.dist-info/METADATA
psychrochart-0.11.1.dist-info/WHEEL
psychrochart-0.11.1.dist-info/RECORD
