Metadata-Version: 2.1
Name: psychrochart
Version: 0.11.1
Summary: A python 3 library to make psychrometric charts and overlay information on them
Home-page: https://github.com/azogue/psychrochart
License: MIT
Keywords: psychrometrics,moist,humid air,climate control,matplotlib
Author: Eugenio Panadero
Author-email: eugenio.panadero@gmail.com
Requires-Python: >=3.10,<3.14
Classifier: Development Status :: 5 - Production/Stable
Classifier: Intended Audience :: Developers
Classifier: Intended Audience :: Education
Classifier: Intended Audience :: Information Technology
Classifier: Intended Audience :: Science/Research
Classifier: License :: OSI Approved :: MIT License
Classifier: Operating System :: OS Independent
Classifier: Programming Language :: Python :: 3
Classifier: Programming Language :: Python :: 3.10
Classifier: Programming Language :: Python :: 3.11
Classifier: Programming Language :: Python :: 3.12
Classifier: Topic :: Scientific/Engineering :: Information Analysis
Classifier: Topic :: Scientific/Engineering :: Physics
Classifier: Topic :: Scientific/Engineering :: Visualization
Requires-Dist: matplotlib (>=3.7)
Requires-Dist: psychrolib (>=2.5)
Requires-Dist: pydantic (>=2.3.0)
Requires-Dist: python-slugify (>=8.0.1)
Project-URL: Repository, https://github.com/azogue/psychrochart
